MANIFEST.in
Makefile
README
setup.py
test/__init__.py
test/__init__.pyc
test/test_compile.py
test/test_post_form.py
test/__pycache__/test_compile.cpython-27-PYTEST.pyc
test/__pycache__/test_post_form.cpython-27-PYTEST.pyc
tiddlywebplugins/__init__.py
tiddlywebplugins/methodhack.py
tiddlywebplugins.methodhack.egg-info/PKG-INFO
tiddlywebplugins.methodhack.egg-info/SOURCES.txt
tiddlywebplugins.methodhack.egg-info/dependency_links.txt
tiddlywebplugins.methodhack.egg-info/namespace_packages.txt
tiddlywebplugins.methodhack.egg-info/not-zip-safe
tiddlywebplugins.methodhack.egg-info/requires.txt
tiddlywebplugins.methodhack.egg-info/top_level.txt