Metadata-Version: 1.0
Name: tiddlywebplugins.methodhack
Version: 0.4
Summary: Allow PUT and DELETE to tunnel over POST
Home-page: http://pypi.python.org/pypi/tiddlywebplugins.methodhack
Author: Chris Dent
Author-email: cdent@peermore.com
License: UNKNOWN
Platform: Posix; MacOS X; Windows
